reactives/__init__.py
reactives/_callable.py
reactives/_decorator.py
reactives/collections.py
reactives/function.py
reactives/py.typed
reactives/reactor.py
reactives/scope.py
reactives/instance/__init__.py
reactives/instance/method.py
reactives/instance/property.py
reactives/tests/__init__.py
reactives/tests/test__callable.py
reactives/tests/test_collections.py
reactives/tests/test_function.py
reactives/tests/test_reactor.py
reactives/tests/test_scope.py
reactives/tests/instance/__init__.py
reactives/tests/instance/test___init__.py
reactives/tests/instance/test_method.py
reactives/tests/instance/test_property.py
reactives-0.5.1.data/data/LICENSE.txt
reactives-0.5.1.data/data/README.md
reactives-0.5.1.data/data/VERSION
reactives-0.5.1.dist-info/LICENSE.txt
reactives-0.5.1.dist-info/METADATA
reactives-0.5.1.dist-info/WHEEL
reactives-0.5.1.dist-info/top_level.txt
reactives-0.5.1.dist-info/RECORD
