Metadata-Version: 2.1
Name: reactives
Version: 0.5.1
Summary: A declarative reactive programming framework.
Home-page: https://github.com/bartfeenstra/reactives
Author: Bart Feenstra & contributors
Author-email: bart@mynameisbart.com
License: GPLv3
Classifier: Intended Audience :: Developers
Classifier: License :: OSI Approved :: GNU General Public License v3 (GPLv3)
Classifier: Programming Language :: Python :: 3.8
Classifier: Programming Language :: Python :: 3.9
Classifier: Programming Language :: Python :: 3.10
Classifier: Programming Language :: Python :: 3.11
Classifier: Topic :: Software Development :: Libraries :: Application Frameworks
Classifier: Typing :: Typed
Requires-Python: ~= 3.8
License-File: LICENSE.txt
Requires-Dist: typing-extensions (>=4.4.0,~=4.4) ; python_version < "3.11"
Requires-Dist: graphlib-backport (>=1.0.3,~=1.0) ; python_version < "3.9"
Provides-Extra: development
Requires-Dist: autopep8 (>=2.0.2,~=2.0) ; extra == 'development'
Requires-Dist: codecov (>=2.1.12,~=2.1) ; extra == 'development'
Requires-Dist: coverage (>=7.2.4,~=7.2) ; extra == 'development'
Requires-Dist: dill (>=0.3.4,~=0.3) ; extra == 'development'
Requires-Dist: flake8 (>=6.0.0,~=6.0) ; extra == 'development'
Requires-Dist: mypy (>=1.2.0,~=1.2) ; extra == 'development'
Requires-Dist: parameterized (>=0.9.0,~=0.9) ; extra == 'development'
Requires-Dist: pytest (>=7.3.1,~=7.3) ; extra == 'development'
Requires-Dist: pytest-cov (>=4.0.0,~=4.0) ; extra == 'development'
Requires-Dist: setuptools (>=67.7.2,~=67.7) ; extra == 'development'
Requires-Dist: twine (>=4.0.2,~=4.0) ; extra == 'development'
Requires-Dist: wheel (>=0.40.0,~=0.40) ; extra == 'development'
